chembox/__init__.py
chembox/chembox.py
chembox/data/conjugates.csv
chembox/data/elements.csv
chembox-1.1.0.dist-info/METADATA
chembox-1.1.0.dist-info/WHEEL
chembox-1.1.0.dist-info/LICENSE
chembox-1.1.0.dist-info/RECORD
