Metadata-Version: 2.1
Name: chembox
Version: 1.1.0
Summary: A package to analyze chemical formulas
License: MIT
Author: Wilfred Hass
Requires-Python: >=3.9
Classifier: License :: OSI Approved :: MIT License
Classifier: Programming Language :: Python :: 3
Classifier: Programming Language :: Python :: 3.9
Classifier: Programming Language :: Python :: 3.10
Classifier: Programming Language :: Python :: 3.11
Requires-Dist: matplotlib (>=3.4.3)
Requires-Dist: pandas (>=1.5.2)
Requires-Dist: python-semantic-release (>=7.33.0,<8.0.0)
